CEA_Wrap/__init__.py
CEA_Wrap/__main__.py
CEA_Wrap/cea_interface.py
CEA_Wrap/mydifflib.py
CEA_Wrap/thermo_lib.py
CEA_Wrap/utils.py
CEA_Wrap/utils_low.py
CEA_Wrap/version.txt
CEA_Wrap/wrapper.py
CEA_Wrap/assets/CEA_Mathematical_Analysis.pdf
CEA_Wrap/assets/CEA_Users_Manual_and_Program_Description.pdf
CEA_Wrap/assets/Dan_CEA2.exe
CEA_Wrap/assets/FCEA2.exe
CEA_Wrap/assets/__init__.py
CEA_Wrap/assets/cea.inc
CEA_Wrap/assets/cea2.f
CEA_Wrap/assets/dan_cea2.f
CEA_Wrap/assets/dan_cea2.inc
CEA_Wrap/assets/thermo.lib
CEA_Wrap/assets/thermo_spg.inp
CEA_Wrap/assets/thermo_spg.out
CEA_Wrap/assets/trans.lib
cea_wrap-2.1.1.dist-info/licenses/LICENSE
cea_wrap-2.1.1.dist-info/METADATA
cea_wrap-2.1.1.dist-info/WHEEL
cea_wrap-2.1.1.dist-info/top_level.txt
cea_wrap-2.1.1.dist-info/RECORD
