Metadata-Version: 2.4
Name: CEA_Wrap
Version: 2.1.1
Summary: A Python-Based wrapper for the NASA CEA Thermochemical Code
Home-page: https://github.com/civilwargeeky/CEA_Wrap
Author: Daniel Klinger
Author-email: klingerd@purdue.edu
License: GNU GPL
Requires: a
Requires: p
Requires: p
Requires: d
Requires: i
Requires: r
Requires: s
Requires-Python: >=3.6
License-File: LICENSE
Requires-Dist: appdirs
Dynamic: author
Dynamic: author-email
Dynamic: description
Dynamic: description-content-type
Dynamic: home-page
Dynamic: license-file
Dynamic: requires
Dynamic: requires-dist
Dynamic: requires-python
Dynamic: summary
